landscape-pdf/__init__.py
landscape-pdf/rotate.py
landscape_pdf/__init__.py
landscape_pdf/rotate.py
landscape_pdf-0.0.2.data/scripts/landscape-pdf
landscape_pdf-0.0.2.dist-info/LICENSE
landscape_pdf-0.0.2.dist-info/METADATA
landscape_pdf-0.0.2.dist-info/WHEEL
landscape_pdf-0.0.2.dist-info/top_level.txt
landscape_pdf-0.0.2.dist-info/RECORD
